{
    "type": "script",
    "id": "30fc5514-5da1-45a2-b6de-dff6c111a99d",
    "name": "Interact with Super Gluey",
    "propId": "7835cc20-43ad-41ed-b6fb-5c4b3a49599d",
    "actorId": null,
    "trigger": {
        "type": "triggers.interact",
        "name": "Interact"
    },
    "entryPoints": [
        {
            "type": "scripts.entryPoint",
            "id": "774c557c-23b6-44d5-97d6-616dc35fb9a7",
            "name": "Main",
            "nodes": [
                {
                    "type": "nodes.showMenu",
                    "id": "ef8f1128-474f-454a-9e4c-c89d370eeabc",
                    "options": [
                        {
                            "type": "options.text",
                            "id": "76bf4157-89f5-45f7-b42d-0798cf31ca1b",
                            "text": "Examine the Super Gluey",
                            "nodes": [
                                {
                                    "type": "nodes.speak",
                                    "id": "73172212-9f33-410c-8eba-21a78adb5379",
                                    "actorId": "30ee2636-15e3-452e-a2db-09cbb9012970",
                                    "text": "It's a bottle of the gluiest glue that ever glued a glue.",
                                    "emotion": "0",
                                    "emotion2": "0",
                                    "device": "0",
                                    "device2": "0"
                                },
                                {
                                    "type": "nodes.speak",
                                    "id": "8120037f-167a-48fb-a466-9a8c4f8eea58",
                                    "actorId": "30ee2636-15e3-452e-a2db-09cbb9012970",
                                    "actorId2": null,
                                    "text": "But what I want to know is, how come it doesn't stick to the inside of the bottle?",
                                    "emotion": "0",
                                    "emotion2": "0",
                                    "device": "0",
                                    "device2": "0"
                                }
                            ],
                            "expression": null,
                            "ignoreChildAvailability": true,
                            "minutes": 0,
                            "ExitMenu": false
                        },
                        {
                            "type": "options.text",
                            "id": "3cf3a5ad-dcc3-4405-8092-7046ffd57d2f",
                            "text": "Touch the Super Gluey",
                            "nodes": [
                                {
                                    "type": "nodes.speak",
                                    "id": "5653f921-9f1c-4d37-9bf6-5d121adc138c",
                                    "actorId": "30ee2636-15e3-452e-a2db-09cbb9012970",
                                    "actorId2": null,
                                    "text": "I'm too smart to touch this stuff.",
                                    "emotion": "0",
                                    "emotion2": "0",
                                    "device": "0",
                                    "device2": "0"
                                },
                                {
                                    "type": "nodes.speak",
                                    "id": "5f5eca56-6e98-473f-9a1f-5fd2a6bb3e37",
                                    "actorId": "30ee2636-15e3-452e-a2db-09cbb9012970",
                                    "actorId2": null,
                                    "text": "And that's coming from someone who, as people say, doesn't have a glue.",
                                    "emotion": "1",
                                    "emotion2": "0",
                                    "device": "0",
                                    "device2": "0"
                                }
                            ],
                            "expression": null,
                            "ignoreChildAvailability": true,
                            "minutes": "1",
                            "ExitMenu": false
                        }
                    ],
                    "AutoAddDone": true,
                    "Unique": false
                }
            ]
        }
    ]
}