{
    "type": "script",
    "id": "490dae3b-df40-4f2f-9863-8fe7ed255cb2",
    "name": "Interact with Plaque Raymond (Ghost)",
    "sceneId": "72d81484-b84f-475d-940b-c354978b3248",
    "propId": "418c9483-00ac-48bd-a20b-bd1479ae78f2",
    "actorId": null,
    "trigger": {
        "type": "triggers.interact",
        "name": "Interact"
    },
    "entryPoints": [
        {
            "type": "scripts.entryPoint",
            "id": "98657ed6-4ca2-43c5-91e6-35ef8810c41f",
            "name": "Main",
            "nodes": [
                {
                    "type": "nodes.showCloseUp",
                    "imageName": "Catacombs_plaque_magicuser_1.png"
                },
                {
                    "type": "nodes.speak",
                    "id": "3b36bfc8-cb4e-4d60-b02a-51d6cbb9dda3",
                    "actorId": "30ee2636-15e3-452e-a2db-09cbb9012970",
                    "actorId2": null,
                    "text": "The plaque reads...",
                    "emotion": "0",
                    "emotion2": "0",
                    "device": "0",
                    "device2": "0"
                },
                {
                    "type": "nodes.speak",
                    "id": "59ef6aeb-cd21-40a8-99c8-113fc90f0d73",
                    "actorId": "30ee2636-15e3-452e-a2db-09cbb9012970",
                    "actorId2": null,
                    "text": "\"There once was a teacher named Ray,\nWhose cooking was terribly fey.\"",
                    "emotion": "0",
                    "emotion2": "0",
                    "device": "0",
                    "device2": "0"
                },
                {
                    "type": "nodes.speak",
                    "id": "b8356143-2a4a-4356-a866-c41ca7b09ef9",
                    "actorId": "30ee2636-15e3-452e-a2db-09cbb9012970",
                    "actorId2": null,
                    "text": "\"The food always was scorched.\nNo one passed the first course.\"",
                    "emotion": "0",
                    "emotion2": "0",
                    "device": "0",
                    "device2": "0"
                },
                {
                    "type": "nodes.speak",
                    "id": "d6b85635-ebc2-4cbe-825d-cf185c96f1eb",
                    "actorId": "30ee2636-15e3-452e-a2db-09cbb9012970",
                    "actorId2": null,
                    "text": "\"Even the water was all burned away.\"",
                    "emotion": "0",
                    "emotion2": "0",
                    "device": "0",
                    "device2": "0"
                },
                {
                    "type": "nodes.onceOnly",
                    "id": "59666035-a8f4-4857-b90d-8f0e083e73fb",
                    "nodes": [
                        {
                            "type": "nodes.speak",
                            "id": "07fa5f17-1665-4f3d-957e-11fc87c27b8c",
                            "actorId": "30ee2636-15e3-452e-a2db-09cbb9012970",
                            "actorId2": null,
                            "text": "I'm glad he isn't the cooking instructor for Hero-U.",
                            "emotion": "1",
                            "emotion2": "0",
                            "device": "0",
                            "device2": "0"
                        }
                    ]
                },
                {
                    "type": "nodes.hideCloseUp",
                    "waitForSeconds": 1
                },
                {
                    "type": "nodes.playSoundEffect",
                    "soundEffectName": "magic_twinkle_loop.wav",
                    "wait": false
                },
                {
                    "type": "nodes.turnActor",
                    "actorId": "30ee2636-15e3-452e-a2db-09cbb9012970",
                    "propId": "15532050-fe54-4ead-abd6-43b2aabc60c4",
                    "wait": true,
                    "scope": "prop",
                    "targetActorId": null
                },
                {
                    "type": "nodes.placeActor",
                    "actorId": "bb406688-04e4-4c93-aaaf-52084b6f975e",
                    "spawnId": "15532050-fe54-4ead-abd6-43b2aabc60c4",
                    "pose": null,
                    "behaviour": "Ghost",
                    "immediate": null
                },
                {
                    "type": "nodes.onceOnly",
                    "id": "87f1da84-17dd-4cc9-89f7-fb4a0e19b957",
                    "nodes": [
                        {
                            "type": "nodes.playAnimation",
                            "actorId": "30ee2636-15e3-452e-a2db-09cbb9012970",
                            "animationName": "JumpScare",
                            "wait": false
                        },
                        {
                            "type": "nodes.speak",
                            "id": "c874e5ee-5a51-4f42-a6fe-2e9e35887e2c",
                            "actorId": "30ee2636-15e3-452e-a2db-09cbb9012970",
                            "actorId2": null,
                            "text": "Oops!",
                            "emotion": "4",
                            "emotion2": "0",
                            "device": "0",
                            "device2": "0"
                        }
                    ]
                },
                {
                    "type": "nodes.branch",
                    "sections": [
                        {
                            "type": "nodes.branchSection",
                            "expression": {
                                "type": "expressions.inInventory",
                                "propId": "34e8cb8d-654c-4e30-81d2-11a9e533e39e",
                                "sceneId": "a2508b7e-a177-4a96-93bd-4d8ab88dffc4",
                                "has": true
                            },
                            "nodes": [
                                {
                                    "type": "nodes.speak",
                                    "id": "7b22f1e8-bfd2-4a40-b6c8-8e941141eccb",
                                    "actorId": "bb406688-04e4-4c93-aaaf-52084b6f975e",
                                    "actorId2": "30ee2636-15e3-452e-a2db-09cbb9012970",
                                    "text": "My cooking skills were really great,\nIf you did not taste what was on your plate.\nYour hero skills will be good, too\nIt all depends on what you do.",
                                    "emotion": "1",
                                    "emotion2": "4",
                                    "device": "0",
                                    "device2": "0"
                                },
                                {
                                    "type": "nodes.branch",
                                    "sections": [
                                        {
                                            "type": "nodes.branchSection",
                                            "expression": {
                                                "type": "expressions.and",
                                                "left": {
                                                    "type": "expressions.variableComparison",
                                                    "variableScope": "global",
                                                    "variableName": "time.day",
                                                    "operator": "gte",
                                                    "compareTo": "32",
                                                    "sceneId": "cbb5c07c-7918-4558-8c19-e4ed45b19ba2",
                                                    "propId": null
                                                },
                                                "right": {
                                                    "type": "expressions.variableComparison",
                                                    "variableScope": "global",
                                                    "variableName": "time.day",
                                                    "operator": "lte",
                                                    "compareTo": "33",
                                                    "sceneId": "cbb5c07c-7918-4558-8c19-e4ed45b19ba2",
                                                    "propId": null
                                                }
                                            },
                                            "nodes": [
                                                {
                                                    "type": "nodes.speak",
                                                    "id": "8813ff08-b33f-4491-ba9d-f314c329ee46",
                                                    "actorId": "bb406688-04e4-4c93-aaaf-52084b6f975e",
                                                    "actorId2": "30ee2636-15e3-452e-a2db-09cbb9012970",
                                                    "text": "Zac the Wraith has trapped his prey\nAnd drains the very life away.\nYou must be quick to save your friend\nBefore he meets his dire end.\n",
                                                    "emotion": "1",
                                                    "emotion2": "4",
                                                    "device": "0",
                                                    "device2": "0"
                                                }
                                            ]
                                        },
                                        {
                                            "type": "nodes.branchSection",
                                            "expression": {
                                                "type": "expressions.variableComparison",
                                                "variableScope": "global",
                                                "variableName": "time.day",
                                                "operator": "gte",
                                                "compareTo": "41",
                                                "sceneId": "72d81484-b84f-475d-940b-c354978b3248",
                                                "propId": null
                                            },
                                            "nodes": [
                                                {
                                                    "type": "nodes.speak",
                                                    "id": "b5f6193f-95ac-4dcb-a0b1-7addc5c5044a",
                                                    "actorId": "bb406688-04e4-4c93-aaaf-52084b6f975e",
                                                    "actorId2": "30ee2636-15e3-452e-a2db-09cbb9012970",
                                                    "text": "So if you mean to make a stand\nGo past his painting, past the man\nAnd to the darkness bring some light\nThen first you have to master fright.",
                                                    "emotion": "0",
                                                    "emotion2": "0",
                                                    "device": "0",
                                                    "device2": "0"
                                                },
                                                {
                                                    "type": "nodes.speak",
                                                    "id": "6f8c5cb9-9652-4ddc-b2af-6f2c77ebf49b",
                                                    "actorId": "bb406688-04e4-4c93-aaaf-52084b6f975e",
                                                    "actorId2": "30ee2636-15e3-452e-a2db-09cbb9012970",
                                                    "text": "Beyond the chamber of death and pain\nDown to Dire Queen's dark domain.\nSpeak to Spooks to gather clues\nTo learn the proper path to choose.",
                                                    "emotion": "3",
                                                    "emotion2": "0",
                                                    "device": "0",
                                                    "device2": "0"
                                                },
                                                {
                                                    "type": "nodes.speak",
                                                    "id": "0af0c1e4-4df6-4ce6-9f8a-f0c778395a76",
                                                    "actorId": "bb406688-04e4-4c93-aaaf-52084b6f975e",
                                                    "actorId2": "30ee2636-15e3-452e-a2db-09cbb9012970",
                                                    "text": "For although my cooking went awry,\nYou couldn't say I didn't try.\nBut what will people say of you\nIf you don't try what you must do?",
                                                    "emotion": "1",
                                                    "emotion2": "0",
                                                    "device": "0",
                                                    "device2": "0"
                                                }
                                            ]
                                        }
                                    ]
                                }
                            ]
                        },
                        {
                            "type": "nodes.branchSection",
                            "expression": null,
                            "nodes": [
                                {
                                    "type": "nodes.playSoundEffect",
                                    "soundEffectName": "Ghost Wail.wav",
                                    "wait": false
                                },
                                {
                                    "type": "nodes.speak",
                                    "id": "3d614313-5806-457a-bbde-44d5313aaef4",
                                    "actorId": "bb406688-04e4-4c93-aaaf-52084b6f975e",
                                    "actorId2": "30ee2636-15e3-452e-a2db-09cbb9012970",
                                    "text": "Ooooowwwwiiiiooooottt!",
                                    "emotion": "3",
                                    "emotion2": "2",
                                    "device": "0",
                                    "device2": "0"
                                },
                                {
                                    "type": "nodes.speak",
                                    "id": "5859c82e-0b3c-4909-8ec4-e77ef80b4712",
                                    "actorId": "30ee2636-15e3-452e-a2db-09cbb9012970",
                                    "actorId2": null,
                                    "text": "(shrug) Parli Romano? Sprechen Sie Germanisch? Doesn't really matter, I don't speak those either.",
                                    "emotion": "1",
                                    "emotion2": "0",
                                    "device": "0",
                                    "device2": "0"
                                },
                                {
                                    "type": "nodes.invokeScript",
                                    "id": "8dcd1af3-5558-4a97-9988-7144da629c7d",
                                    "scriptId": "98bed7e3-6d3d-4482-ae95-e3913dd384ed",
                                    "entryPointId": "98657ed6-4ca2-43c5-91e6-35ef8810c41f",
                                    "currentScope": "Scenes",
                                    "currentSceneId": "5f4c53b2-540d-4627-af71-7ede35c6d84b",
                                    "currentActorId": null,
                                    "currentStoryEventId": null,
                                    "currentPropId": null
                                }
                            ]
                        }
                    ]
                },
                {
                    "type": "nodes.branch",
                    "sections": [
                        {
                            "type": "nodes.branchSection",
                            "expression": {
                                "type": "expressions.isEquipped",
                                "propId": "840c8a59-3e39-4ede-aa2a-4201ae7ac891",
                                "sceneId": "a2508b7e-a177-4a96-93bd-4d8ab88dffc4"
                            },
                            "nodes": [
                                {
                                    "type": "nodes.changeHealth",
                                    "id": "609793f8-2c86-4996-8f6c-41dcd44e31a8",
                                    "target": "0",
                                    "amount": "-2",
                                    "canDie": false,
                                    "isPercentage": true
                                }
                            ]
                        },
                        {
                            "type": "nodes.branchSection",
                            "expression": null,
                            "nodes": [
                                {
                                    "type": "nodes.changeHealth",
                                    "id": "12af4d24-2c89-4f35-a92a-39b0dae4be38",
                                    "target": "0",
                                    "amount": "-5",
                                    "canDie": false,
                                    "isPercentage": true
                                }
                            ]
                        }
                    ]
                },
                {
                    "type": "nodes.playSoundEffect",
                    "soundEffectName": "magic_teleport.wav",
                    "wait": false
                },
                {
                    "type": "nodes.invokeCommand",
                    "id": "f6880197-2567-4b4c-b969-17e626a90016",
                    "entityType": "actor",
                    "entityId": "bb406688-04e4-4c93-aaaf-52084b6f975e",
                    "command": "fadeout",
                    "wait": true,
                    "resultVariableScope": "script"
                },
                {
                    "type": "nodes.removeActor",
                    "id": "157ea96d-e485-4bae-88db-c494d3efb2b4",
                    "actorId": "bb406688-04e4-4c93-aaaf-52084b6f975e"
                }
            ]
        }
    ]
}